pypyenv
