Metadata-Version: 1.0
Name: pypyenv
Version: 0.1.1
Summary: Install PyPy in virtualenv
Home-page: http://github.com/alexeiboronine/pypyenv
Author: Alexei Boronine
Author-email: alexei.boronine@gmail.com
License: MIT
Download-URL: http://github.com/alexeiboronine/pypyenv/downloads
Keywords: pypy virtualenv
Platform: UNKNOWN
Classifier: Development Status :: 3 - Alpha
Classifier: Intended Audience :: Developers
Classifier: Intended Audience :: System Administrators
Classifier: License :: OSI Approved :: MIT License
Classifier: Operating System :: OS Independent
Classifier: Topic :: Software Development
